{
  "collectionName": "components_block_our_clients_block_our_clients",
  "info": {
    "displayName": "Block Our Clients",
    "description": ""
  },
  "options": {},
  "attributes": {
    "BlockType": {
      "type": "string",
      "required": true,
      "default": "blockOurClientsTestimonials"
    },
    "Title": {
      "type": "string",
      "unique": false
    },
    "Items": {
      "displayName": "Items",
      "type": "component",
      "repeatable": true,
      "component": "block-our-clients.items"
    },
    "Image": {
      "type": "media",
      "multiple": false,
      "required": false,
      "allowedTypes": [
        "images"
      ]
    },
    "ImageAlt": {
      "type": "string"
    }
  }
}
